soft_deletion/__init__.py
soft_deletion/models/__init__.py
soft_deletion/models/base.py
soft_deletion/models/deletion.py
soft_deletion/models/query.py
soft_deletion/models/signals.py
tests/__init__.py
tests/test_settings.py
tests/test_soft_delete.py
django_soft_deletion_model-1.0.0.dist-info/LICENSE
django_soft_deletion_model-1.0.0.dist-info/METADATA
django_soft_deletion_model-1.0.0.dist-info/WHEEL
django_soft_deletion_model-1.0.0.dist-info/top_level.txt
django_soft_deletion_model-1.0.0.dist-info/RECORD
