Metadata-Version: 2.2
Name: django-soft-deletion-model
Version: 1.0.0
Summary: A Django-based library for implementing soft deletion using a deleted_at timestamp.
Home-page: https://github.com/alirafiei75/django-soft-deletion
Author: Ali Rafiei
Author-email: a.rafiei1375@gmail.com
License: MIT
Classifier: Framework :: Django
Classifier: License :: OSI Approved :: MIT License
Classifier: Programming Language :: Python :: 3
Classifier: Development Status :: 4 - Beta
License-File: LICENSE
Requires-Dist: Django==4.2
Dynamic: author
Dynamic: author-email
Dynamic: classifier
Dynamic: description
Dynamic: description-content-type
Dynamic: home-page
Dynamic: license
Dynamic: requires-dist
Dynamic: summary
